lgrt4gps/__init__.py
lgrt4gps/btn.py
lgrt4gps/gp.py
lgrt4gps/kern.py
lgrt4gps/lgrtn.py
lgrt4gps/version.py
lgrt4gps-0.0.2.dist-info/LICENSE
lgrt4gps-0.0.2.dist-info/METADATA
lgrt4gps-0.0.2.dist-info/WHEEL
lgrt4gps-0.0.2.dist-info/entry_points.txt
lgrt4gps-0.0.2.dist-info/top_level.txt
lgrt4gps-0.0.2.dist-info/RECORD
