Metadata-Version: 2.1
Name: lgrt4gps
Version: 0.0.2
Summary: Locally growing random trees for Gaussian processes
Home-page: https://github.com/jumlauft/LGRT4GPs
Author: Jonas Umlauft
Author-email: jumlauft@gmail.com
License: MIT
Platform: UNKNOWN
Classifier: License :: OSI Approved :: MIT License
Classifier: Programming Language :: Python :: 3.6
Classifier: Programming Language :: Python :: 3.7
Classifier: Programming Language :: Python :: 3.8
Requires-Dist: numpy
Requires-Dist: scipy
Requires-Dist: paramz
Requires-Dist: gpy
Requires-Dist: six
Requires-Dist: binarytree
Requires-Dist: matplotlib
